detroit/__init__.py
detroit/types.py
detroit/array/__init__.py
detroit/array/argpass.py
detroit/array/bin.py
detroit/array/blur.py
detroit/array/extent.py
detroit/array/group.py
detroit/array/nice.py
detroit/array/set_operations.py
detroit/array/ticks.py
detroit/array/threshold/__init__.py
detroit/array/threshold/freedman_diaconis.py
detroit/array/threshold/scott.py
detroit/array/threshold/sturges.py
detroit/axis/__init__.py
detroit/axis/axis.py
detroit/chord/__init__.py
detroit/chord/chord.py
detroit/chord/ribbon.py
detroit/color/__init__.py
detroit/color/color.py
detroit/color/cubehelix.py
detroit/color/lab.py
detroit/contour/__init__.py
detroit/contour/area.py
detroit/contour/constant.py
detroit/contour/contains.py
detroit/contour/contours.py
detroit/contour/density.py
detroit/delaunay/__init__.py
detroit/delaunay/context.py
detroit/delaunay/delaunator.py
detroit/delaunay/delaunay.py
detroit/delaunay/orient2d.py
detroit/delaunay/path.py
detroit/delaunay/polygon.py
detroit/delaunay/utils.py
detroit/delaunay/voronoi.py
detroit/ease/__init__.py
detroit/ease/back.py
detroit/ease/bounce.py
detroit/ease/circle.py
detroit/ease/cubic.py
detroit/ease/elastic.py
detroit/ease/exp.py
detroit/ease/linear.py
detroit/ease/poly.py
detroit/ease/quad.py
detroit/ease/sin.py
detroit/ease/tqmt.py
detroit/force/__init__.py
detroit/force/center.py
detroit/force/collide.py
detroit/force/constant.py
detroit/force/jiggle.py
detroit/force/lcg.py
detroit/force/link.py
detroit/force/many_body.py
detroit/force/radial.py
detroit/force/simulation.py
detroit/force/x.py
detroit/force/y.py
detroit/format/__init__.py
detroit/format/default_locale.py
detroit/format/exponent.py
detroit/format/format_decimal.py
detroit/format/format_group.py
detroit/format/format_numerals.py
detroit/format/format_prefix_auto.py
detroit/format/format_rounded.py
detroit/format/format_specifier.py
detroit/format/format_trim.py
detroit/format/format_types.py
detroit/format/identity.py
detroit/format/locale.py
detroit-2.6.0.dist-info/licenses/LICENSE
detroit-2.6.0.dist-info/METADATA
detroit-2.6.0.dist-info/WHEEL
detroit-2.6.0.dist-info/top_level.txt
detroit-2.6.0.dist-info/RECORD
