Metadata-Version: 2.4
Name: detroit
Version: 2.6.0
Summary: detroit is a Python implementation of d3js
Author-email: Benjamin BOURBON <ben.bourbon06@gmail.com>
Project-URL: Homepage, https://github.com/bourbonut/detroit
Project-URL: Repository, https://github.com/bourbonut/detroit
Project-URL: Documentation, https://detroit.readthedocs.io/en/latest/
Classifier: Programming Language :: Python
Classifier: Programming Language :: Python :: 3.10
Classifier: Programming Language :: Python :: 3.11
Classifier: Programming Language :: Python :: 3.12
Classifier: Programming Language :: Python :: 3.13
Classifier: Topic :: Scientific/Engineering :: Visualization
Requires-Python: >=3.10
License-File: LICENSE
Requires-Dist: lxml
Dynamic: license-file
